sonic_wrapper/__init__.py
sonic_wrapper/__main__.py
sonic_wrapper/cli.py
sonic_wrapper/sonic_api_wrapper.py
sonic_wrapper/sonic_wrapper.py
sonic_wrapper-0.1.5.dist-info/METADATA
sonic_wrapper-0.1.5.dist-info/WHEEL
sonic_wrapper-0.1.5.dist-info/RECORD
