Metadata-Version: 2.4
Name: sonic-wrapper
Version: 0.1.5
Summary: A simple wrapper for Cartesia Sonic TTS
Project-URL: Homepage, https://github.com/daswer123/sonic_tts_api_wrapper
Project-URL: Bug Tracker, https://github.com/daswer123/sonic_tts_api_wrapper/issues
Author-email: daswer123 <daswerq123@gmail.com>
Classifier: License :: OSI Approved :: MIT License
Classifier: Operating System :: OS Independent
Classifier: Programming Language :: Python :: 3
Requires-Python: >=3.9
Requires-Dist: cartesia==1.1.0
Requires-Dist: loguru
Requires-Dist: python-dotenv
Requires-Dist: tqdm
